nexusdelta/__init__.py
nexusdelta/exceptions.py
nexusdelta/sdk.py
nexusdelta_sdk-2.0.2.dist-info/licenses/LICENSE
tests/__init__.py
tests/test_firebase_registration.py
tests/test_integration.py
tests/test_sdk.py
tests/test_sdk_v2.py
nexusdelta_sdk-2.0.2.dist-info/METADATA
nexusdelta_sdk-2.0.2.dist-info/WHEEL
nexusdelta_sdk-2.0.2.dist-info/top_level.txt
nexusdelta_sdk-2.0.2.dist-info/RECORD
