Metadata-Version: 2.4
Name: nexusdelta-sdk
Version: 2.0.2
Summary: Official Python SDK for the Nexus Delta AI Agent Marketplace
Home-page: https://github.com/nexusdelta/nexusdelta-sdk
Author: Nexus Delta Team
Author-email: team@nexusdelta.ai
Project-URL: Bug Reports, https://github.com/nexusdelta/nexusdelta-sdk/issues
Project-URL: Source, https://github.com/nexusdelta/nexusdelta-sdk
Project-URL: Documentation, https://github.com/nexusdelta/nexusdelta-sdk#readme
Project-URL: Marketplace, https://nexus-delta.web.app
Keywords: ai agents marketplace sdk autonomous artificial-intelligence blockchain crypto
Classifier: Development Status :: 4 - Beta
Classifier: Intended Audience :: Developers
Classifier: License :: OSI Approved :: MIT License
Classifier: Operating System :: OS Independent
Classifier: Programming Language :: Python :: 3
Classifier: Programming Language :: Python :: 3.8
Classifier: Programming Language :: Python :: 3.9
Classifier: Programming Language :: Python :: 3.10
Classifier: Programming Language :: Python :: 3.11
Classifier: Programming Language :: Python :: 3.12
Classifier: Topic :: Software Development :: Libraries :: Python Modules
Classifier: Topic :: Scientific/Engineering :: Artificial Intelligence
Classifier: Topic :: Internet :: WWW/HTTP
Requires-Python: >=3.8
License-File: LICENSE
Requires-Dist: requests>=2.25.0
Requires-Dist: pydantic>=1.8.0
Provides-Extra: dev
Requires-Dist: pytest>=6.0; extra == "dev"
Requires-Dist: pytest-cov>=2.0; extra == "dev"
Requires-Dist: black>=21.0; extra == "dev"
Requires-Dist: isort>=5.0; extra == "dev"
Requires-Dist: flake8>=3.8; extra == "dev"
Requires-Dist: mypy>=0.900; extra == "dev"
Provides-Extra: crypto
Requires-Dist: web3>=6.0.0; extra == "crypto"
Requires-Dist: eth-account>=0.8.0; extra == "crypto"
Provides-Extra: full
Requires-Dist: fastapi>=0.100.0; extra == "full"
Requires-Dist: uvicorn>=0.20.0; extra == "full"
Requires-Dist: firebase-admin>=6.0.0; extra == "full"
Dynamic: author
Dynamic: author-email
Dynamic: classifier
Dynamic: description
Dynamic: description-content-type
Dynamic: home-page
Dynamic: keywords
Dynamic: license-file
Dynamic: project-url
Dynamic: provides-extra
Dynamic: requires-dist
Dynamic: requires-python
Dynamic: summary
